xyra/__init__.py
xyra/__main__.py
xyra/application.py
xyra/background.py
xyra/concurrency.py
xyra/datastructures.py
xyra/exceptions.py
xyra/logger.py
xyra/params.py
xyra/request.py
xyra/response.py
xyra/routing.py
xyra/swagger.py
xyra/templating.py
xyra/utils.py
xyra/websockets.py
xyra/middleware/__init__.py
xyra/middleware/base.py
xyra/middleware/cors.py
xyra/middleware/csrf.py
xyra/middleware/gzip.py
xyra/middleware/httpsredirect.py
xyra/middleware/rate_limiter.py
xyra/middleware/security_headers.py
xyra/middleware/trustedhost.py
xyra-0.2.1.dist-info/licenses/LICENSE
xyra-0.2.1.dist-info/METADATA
xyra-0.2.1.dist-info/WHEEL
xyra-0.2.1.dist-info/entry_points.txt
xyra-0.2.1.dist-info/top_level.txt
xyra-0.2.1.dist-info/RECORD
