Metadata-Version: 2.4
Name: xyra
Version: 0.2.1
Summary: High Performance Frameworks, Easy to learn and Ready for Production
Author-email: Xyra Team <team@xyra.dev>
Maintainer-email: Xyra Team <team@xyra.dev>
License: MIT
Project-URL: Homepage, https://github.com/xyra-python/xyra
Project-URL: Documentation, https://xyra.dev/docs
Project-URL: Repository, https://github.com/xyra-python/xyra
Project-URL: Issues, https://github.com/xyra-python/xyra/issues
Project-URL: Changelog, https://github.com/xyra-python/xyra/blob/main/CHANGELOG.md
Keywords: web,framework,async,fast,python
Classifier: Development Status :: 3 - Alpha
Classifier: Intended Audience :: Developers
Classifier: License :: OSI Approved :: MIT License
Classifier: Programming Language :: Python :: 3
Classifier: Programming Language :: Python :: 3.11
Classifier: Programming Language :: Python :: 3.12
Classifier: Programming Language :: Python :: 3.13
Classifier: Topic :: Internet :: WWW/HTTP :: HTTP Servers
Classifier: Topic :: Software Development :: Libraries :: Application Frameworks
Requires-Python: >=3.11
License-File: LICENSE
Requires-Dist: socketify
Requires-Dist: jinja2
Requires-Dist: multidict
Requires-Dist: watchfiles
Requires-Dist: orjson>=3.11.3; platform_python_implementation != "PyPy"
Requires-Dist: ujson; platform_python_implementation == "PyPy"
Provides-Extra: dev
Requires-Dist: pytest>=8.4.2; extra == "dev"
Requires-Dist: pytest-asyncio>=1.2.0; extra == "dev"
Requires-Dist: pytest-tornasync>=0.6.0.post2; extra == "dev"
Requires-Dist: pytest-twisted>=0.8.0; extra == "dev"
Requires-Dist: pytest-trio>=0.8.0; extra == "dev"
Requires-Dist: anyio>=4.11.0; extra == "dev"
Requires-Dist: twisted>=25.5.0; extra == "dev"
Requires-Dist: ruff>=0.13.3; extra == "dev"
Requires-Dist: mypy; extra == "dev"
Requires-Dist: black; extra == "dev"
Requires-Dist: isort; extra == "dev"
Requires-Dist: bandit; extra == "dev"
Requires-Dist: pytest-cov; extra == "dev"
Provides-Extra: docs
Requires-Dist: mkdocs; extra == "docs"
Requires-Dist: mkdocs-material; extra == "docs"
Dynamic: license-file
